linkify_it/__init__.py
linkify_it/main.py
linkify_it/tlds.py
linkify_it/ucre.py
linkify_it_py-2.0.2.dist-info/LICENSE
linkify_it_py-2.0.2.dist-info/METADATA
linkify_it_py-2.0.2.dist-info/WHEEL
linkify_it_py-2.0.2.dist-info/top_level.txt
linkify_it_py-2.0.2.dist-info/RECORD
